Workbook
Name aporte_mensal: Simulador!$D$20
Name dividentos: Simulador!$D$24
Name investimento_mensal: Simulador!$D$20
Name patrimonio: Simulador!$D$23
Name Perfil: Simulador!$C$34
Name qtd_anos: Simulador!$D$21
Name rendimento_carteira: Simulador!$D$16
Name salario: Simulador!$D$15
Name sugestao_investimento: Simulador!$D$17
Name taxa_mensal: Simulador!$D$22

Sheet Simulador
B14: CONFIGURAÇÕES
B15: Salário | D15: 2000
B16: Rendimento Carteira | D16: 0.006
B17: Sugestão de Investimento (30%) | D17: =D15*30% -> 600
B19: INVESTIMENTO MENSAL
B20: Quanto investir por mês? | D20: 200
B21: Por quantos anos? | D21: 5
B22: Taxa de rendimento mensal? | D22: 0.01079
B23: Patrimônio Acumulado | D23: =FV(taxa_mensal,qtd_anos*12,aporte_mensal*-1) -> 16755.383
B24: Dividendos Mensais | D24: =patrimonio*rendimento_carteira -> 100.5323
B26: Cenários | C26: Patrimônio | D26: Dividendo
A27: 2 | B27: Quanto em 2 anos? | C27: =FV(taxa_mensal,$A27*12,investimento_mensal*-1) -> 5445.5255 | D27: =C27*rendimento_carteira -> 32.673153
A28: 5 | B28: Quanto em 5 anos? | C28: =FV(taxa_mensal,$A28*12,investimento_mensal*-1) -> 16755.383 | D28: =C28*rendimento_carteira -> 100.5323
A29: 10 | B29: Quanto em 10 anos? | C29: =FV(taxa_mensal,$A29*12,investimento_mensal*-1) -> 48656.843 | D29: =C29*rendimento_carteira -> 291.94106
A30: 20 | B30: Quanto em 20 anos? | C30: =FV(taxa_mensal,$A30*12,investimento_mensal*-1) -> 225039.68 | D30: =C30*rendimento_carteira -> 1350.2381
A31: 30 | B31: Quanto em 30 anos? | C31: =FV(taxa_mensal,$A31*12,investimento_mensal*-1) -> 864433.93 | D31: =C31*rendimento_carteira -> 5186.6036
B34: PERFIL | C34: Moderado
B35: VALOR A SER INVESTIDO POR MÊS | C35: =aporte_mensal -> 200
B37: TIPO DE FII | C37: Percentual Sugerido | D37: Valores
A38: =_xlfn.CONCAT(Perfil,"-",B38) -> Moderado-PAPEL | B38: PAPEL | C38: =VLOOKUP(_xlfn.CONCAT(Perfil,"-",B38),'tabela apoio'!$A$2:$D$20,4,0) -> 0.32 | D38: =IF(aporte_mensal*C38=0,"-",aporte_mensal*C38) -> 64
A39: =_xlfn.CONCAT(Perfil,"-",B39) -> Moderado-TIJOLO | B39: TIJOLO | C39: =VLOOKUP(_xlfn.CONCAT(Perfil,"-",B39),'tabela apoio'!$A$2:$D$20,4,0) -> 0.35 | D39: =IF(aporte_mensal*C39=0,"-",aporte_mensal*C39) -> 70
A40: =_xlfn.CONCAT(Perfil,"-",B40) -> Moderado-HÍBRIDO | B40: HÍBRIDO | C40: =VLOOKUP(_xlfn.CONCAT(Perfil,"-",B40),'tabela apoio'!$A$2:$D$20,4,0) -> 0.08 | D40: =IF(aporte_mensal*C40=0,"-",aporte_mensal*C40) -> 16
A41: =_xlfn.CONCAT(Perfil,"-",B41) -> Moderado-FOFs | B41: FOFs | C41: =VLOOKUP(_xlfn.CONCAT(Perfil,"-",B41),'tabela apoio'!$A$2:$D$20,4,0) -> 0.05 | D41: =IF(aporte_mensal*C41=0,"-",aporte_mensal*C41) -> 10
A42: =_xlfn.CONCAT(Perfil,"-",B42) -> Moderado-DESENVOLVIMENTO | B42: DESENVOLVIMENTO | C42: =VLOOKUP(_xlfn.CONCAT(Perfil,"-",B42),'tabela apoio'!$A$2:$D$20,4,0) -> 0.1 | D42: =IF(aporte_mensal*C42=0,"-",aporte_mensal*C42) -> 20
A43: =_xlfn.CONCAT(Perfil,"-",B43) -> Moderado-HOSPITALIDADE | B43: HOSPITALIDADE | C43: =VLOOKUP(_xlfn.CONCAT(Perfil,"-",B43),'tabela apoio'!$A$2:$D$20,4,0) -> 0.1 | D43: =IF(aporte_mensal*C43=0,"-",aporte_mensal*C43) -> 20
B44: TOTAL | D44: =SUM(D38:D43) -> 200

Sheet tabela apoio
A2: CHAVE | B2: PERFIL | C2: TIPO DE FII | D2: %
A3: =_xlfn.CONCAT(B3,"-",C3) -> Conservador-PAPEL | B3: Conservador | C3: PAPEL | D3: 0.3
A4: =_xlfn.CONCAT(B4,"-",C4) -> Conservador-TIJOLO | B4: Conservador | C4: TIJOLO | D4: 0.5
A5: =_xlfn.CONCAT(B5,"-",C5) -> Conservador-HÍBRIDO | B5: Conservador | C5: HÍBRIDO | D5: 0.1
A6: =_xlfn.CONCAT(B6,"-",C6) -> Conservador-FOFs | B6: Conservador | C6: FOFs | D6: 0.1
A7: =_xlfn.CONCAT(B7,"-",C7) -> Conservador-DESENVOLVIMENTO | B7: Conservador | C7: DESENVOLVIMENTO | D7: 0
A8: =_xlfn.CONCAT(B8,"-",C8) -> Conservador-HOSPITALIDADE | B8: Conservador | C8: HOSPITALIDADE | D8: 0
A9: =_xlfn.CONCAT(B9,"-",C9) -> Moderado-PAPEL | B9: Moderado | C9: PAPEL | D9: 0.32
A10: =_xlfn.CONCAT(B10,"-",C10) -> Moderado-TIJOLO | B10: Moderado | C10: TIJOLO | D10: 0.35
A11: =_xlfn.CONCAT(B11,"-",C11) -> Moderado-HÍBRIDO | B11: Moderado | C11: HÍBRIDO | D11: 0.08
A12: =_xlfn.CONCAT(B12,"-",C12) -> Moderado-FOFs | B12: Moderado | C12: FOFs | D12: 0.05
A13: =_xlfn.CONCAT(B13,"-",C13) -> Moderado-DESENVOLVIMENTO | B13: Moderado | C13: DESENVOLVIMENTO | D13: 0.1
A14: =_xlfn.CONCAT(B14,"-",C14) -> Moderado-HOSPITALIDADE | B14: Moderado | C14: HOSPITALIDADE | D14: 0.1
... A20: =_xlfn.CONCAT(B20,"-",C20) -> Agressivo-HOSPITALIDADE | B20: Agressivo | C20: HOSPITALIDADE | D20: 0.1
